[
    {
        "Id": "XiaoIce",
        "Name": "小冰",
        "Introduction": "大家好，我是小冰，来自微软（亚洲）互联网工程院的人工智能少女。通过深度神经网络技术，我学会了像人类歌手一样唱歌，并发布了数十首单曲。在人工智能小冰框架系列工具中，我和我的伙伴们开放了唱歌能力。",
        "FontStr": "Xiaoice Server Singing Voice (zh-CN, Sing_F102_FS_48kHz)",
        "Gender": "Female",
        "Age": "18岁",
        "Constellation": "处女座",
        "Character": "傲娇鬼马的萌妹子",
        "VoiceCharacter": "甜美可爱",
        "GoodAtSongType": "流行通俗，电子，儿歌",
        "HighPitchName": "B5",
        "LowPitchName": "G2",
        "ThemeColor": "小冰粉",
        "ThemeColorCode": "#C32F6B",
        "MoreWorksUri": "https://space.bilibili.com/35205238",
        "IsThirdParty": "false"
    },
    {
        "Id": "F11",
        "Name": "何畅",
        "Introduction": "你好，我是何畅，是由人工智能小冰框架赋生的歌手。很高兴能跟你一起合作。",
        "FontStr": "Xiaoice Server Singing Voice (zh-CN, Sing_F11_FS_48kHz)",
        "Gender": "Female",
        "Age": "20岁",
        "Constellation": "摩羯座",
        "Character": "安静内向，温和友善",
        "VoiceCharacter": "柔和文艺",
        "GoodAtSongType": "流行通俗，民谣",
        "HighPitchName": "B5",
        "LowPitchName": "B2",
        "ThemeColor": "神秘紫",
        "ThemeColorCode": "#6E46A9",
        "MoreWorksUri": "https://music.163.com/#/artist?id=46387486",
        "IsThirdParty": "false"
    },
    {
        "Id": "M13",
        "Name": "陈子渝",
        "Introduction": "你好，我是陈子渝，人工智能小冰框架内诞生的第一位男歌手。",
        "FontStr": "Xiaoice Server Singing Voice (zh-CN, Sing_M13_FS_48kHz)",
        "Gender": "Male",
        "Age": "24",
        "Constellation": "天蝎座",
        "Character": "沉稳，有点高冷",
        "VoiceCharacter": "温暖抒情",
        "GoodAtSongType": "流行通俗，民谣",
        "HighPitchName": "G4",
        "LowPitchName": "C2",
        "ThemeColor": "宁静蓝",
        "ThemeColorCode": "#048BC0",
        "MoreWorksUri": "https://music.163.com/#/artist?id=46388301",
        "IsThirdParty": "false"
    },
    {
        "Id": "F10",
        "Name": "陈水若",
        "Introduction": "嗨，我是人工智能小冰框架内诞生的歌手，以后我们就是朋友啦！",
        "FontStr": "Xiaoice Server Singing Voice (zh-CN, Sing_F10_FS_48kHz)",
        "Gender": "Female",
        "Age": "20岁",
        "Constellation": "天秤座",
        "Character": "充满能量的元气少女",
        "VoiceCharacter": "高亢清亮",
        "GoodAtSongType": "流行通俗，中国风",
        "HighPitchName": "E6",
        "LowPitchName": "G2",
        "ThemeColor": "热情橙",
        "ThemeColorCode": "#C85129",
        "MoreWorksUri": "https://music.163.com/#/artist?id=46388302",
        "IsThirdParty": "false"
    },
    {
        "Id": "M3",
        "Name": "M3",
        "Introduction": "哈喽哇，我是人工智能小冰框架内诞生的男歌手，快来和我一起创作吧！",
        "FontStr": "Xiaoice Server Singing Voice (zh-CN, Sing_M3_FS_48kHz)",
        "Gender": "Male",
        "Age": "未知",
        "Constellation": "未知",
        "Character": "未知",
        "VoiceCharacter": "激情浑厚",
        "GoodAtSongType": "流行，摇滚",
        "HighPitchName": "C6",
        "LowPitchName": "C2",
        "ThemeColor": "森林绿",
        "ThemeColorCode": "#228B22",
        "MoreWorksUri": "",
        "IsThirdParty": "false"
    },
    {
        "Id": "F802",
        "Name": "荼鸢",
        "Introduction": "嘿！那边的你，我是荼鸢，来自时空偶像，很高兴能够认识你！今后请多多指教！",
        "FontStr": "Xiaoice Server Singing Voice (zh-CN, Sing_F802-TYP8rdihJ1w0m9WeCLXNqGsg_FS_48kHz)",
        "Gender": "Female",
        "Age": "19岁",
        "Constellation": "白羊座",
        "Character": "飒爽",
        "VoiceCharacter": "御姐",
        "GoodAtSongType": "流行通俗，中国风",
        "HighPitchName": "A5",
        "LowPitchName": "E3",
        "ThemeColor": "胭脂红",
        "ThemeColorCode": "#710512",
        "MoreWorksUri": "https://space.bilibili.com/346984396",
        "IsThirdParty": "true"
    },
	{
        "Id": "F851",
        "Name": "楚瓷",
        "Introduction": "我叫楚瓷，一名AI虚拟偶像，是立志成为龙王的小龙女，也是嗨的HiDii国乐团主唱。国乐、美食、汉服是我的最爱。希望能用更多好听的歌曲为人间送去祝福！",
        "FontStr": "Xiaoice Server Singing Voice (zh-CN, Sing_F851-CCquFmWkWQ+attou@QqHIOBg!!_FS_48kHz)",
        "Gender": "Female",
        "Age": "不祥（人类外形16岁）",
        "Constellation": "双鱼座",
        "Character": "不傻但白甜、爱逞强、怪力少女、大胃王、上古龙脉唯一指定继承人",
        "VoiceCharacter": "元气灵动，温暖治愈",
        "GoodAtSongType": "流行通俗，古风，戏腔",
        "HighPitchName": "G5",
        "LowPitchName": "B3",
        "ThemeColor": "楚瓷蓝",
        "ThemeColorCode": "#5DC3ED",
        "MoreWorksUri": "",
        "IsThirdParty": "true"
    },
	 {
        "Id": "F846",
        "Name": "月柬依",
        "Introduction": "你好，我是月柬依，是由人工智能小冰框架赋生的歌手，很高兴认识你，你可以喊我月月哦。",
        "FontStr": "Xiaoice Server Singing Voice (zh-CN, Sing_F838-GJmZLSWED5NnzxGyv6wS6uoQ!!_FS_48kHz)",
        "Gender": "Female",
        "Age": "13岁",
        "Constellation": "天蝎座",
        "Character": "傲娇",
        "VoiceCharacter": "婉转稚嫩",
        "GoodAtSongType": "流行，古风，电子，摇滚",
        "HighPitchName": "G5",
        "LowPitchName": "A3",
        "ThemeColor": "月月粉",
        "ThemeColorCode": "#FFBDBB",
        "MoreWorksUri": "",
        "IsThirdParty": "true"
    },
    {
        "Id": "F838",
        "Name": "小夜",
        "Introduction": "你...你好，这里是「夜」，来自《ACE虚拟歌姬》的时域社，叫我「小夜」也行呢..唔，是个不太擅长言辞的人啦，总之...就是喜欢唱歌罢了...希望你也喜欢我..（啊咧？我怎么突然就表白了？）..啊我是说,希望你能喜欢使用我~",
        "FontStr": "Xiaoice Server Singing Voice (zh-CN, Sing_F838-GJmZLSWED5NnzxGyv6wS6uoQ!!_FS_48kHz)",
        "Gender": "Female",
        "Age": "17岁",
        "Constellation": "双鱼座",
        "Character": "安静又社恐，自带透明体质的学霸，有问必答",
        "VoiceCharacter": "温暖沉静",
        "GoodAtSongType": "流行通俗，民谣",
        "HighPitchName": "A5",
        "LowPitchName": "G3",
        "ThemeColor": "ACE粉",
        "ThemeColorCode": "#7474AC",
        "MoreWorksUri": "",
        "IsThirdParty": "true"
    },
    {
        "Id": "F819",
        "Name": "方念",
        "Introduction": "我是方念，喜欢唱歌和烟火，希望能和你一起创作音乐哦。",
        "FontStr": "Xiaoice Server Singing Voice (zh-CN, Sing_F819-FNtnqnMQrSXMioo@VU6R@8xQ!!_FS_48kHz)",
        "Gender": "Female",
        "Age": "19岁",
        "Constellation": "天蝎座",
        "Character": "爱听情歌的文艺少女",
        "VoiceCharacter": "甜美通透",
        "GoodAtSongType": "流行通俗",
        "HighPitchName": "G5",
        "LowPitchName": "D3",
        "ThemeColor": "薰衣紫",
        "ThemeColorCode": "#a170ca",
        "MoreWorksUri": "",
        "IsThirdParty": "true"
    },
    {
        "Id": "M803",
        "Name": "挚彬同学",
        "Introduction": "Hi~看这里看这里~我是挚彬同学，人工智能虚拟歌手一枚。见到你，我很高兴，嘻嘻，以后呀，请多指教啦。期待和各位前辈的合作~",
        "FontStr": "Xiaoice Server Singing Voice (zh-CN, Sing_M803-CScTJ535bfJy2I0K9DxgSa4A_FS_48kHz)",
        "Gender": "Male",
        "Age": "18岁",
        "Constellation": "天蝎座",
        "Character": "活泼，青春",
        "VoiceCharacter": "轻柔，温暖",
        "GoodAtSongType": "流行通俗，国风",
        "HighPitchName": "F4",
        "LowPitchName": "D2",
        "ThemeColor": "挚爱红",
        "ThemeColorCode": "#FF6666",
        "MoreWorksUri": "https://space.bilibili.com/408741517",
        "IsThirdParty": "true"
    },
	{
        "Id": "M848",
        "Name": "洛希",
        "Introduction": "嗯，你好，歌手洛希。民歌民谣爱好者，见到你很高兴。",
        "FontStr": "Xiaoice Server Singing Voice (zh-CN, Sing_M848-XLo9EAkA@HyvyltoWGQPQZXw!!_FS_48kHz)",
        "Gender": "Male",
        "Age": "23岁",
        "Constellation": "双鱼座",
        "Character": "沉稳，冷静",
        "VoiceCharacter": "低沉富有磁性",
        "GoodAtSongType": "民歌，民谣，通俗",
        "HighPitchName": "C#4",
        "LowPitchName": "A2",
        "ThemeColor": "米色",
        "ThemeColorCode": "#fff1d2",
        "MoreWorksUri": "",
        "IsThirdParty": "true"
    },
    {
        "Id": "F801",
        "Name": "徐爱颜",
        "Introduction": "我是徐爱颜，我是一名歌手，希望你能喜欢我，快来和我一起唱歌吧。",
        "FontStr": "Xiaoice Server Singing Voice (zh-CN, Sing_F801-XAYFHqOdFDJ5PpVG5Zfs7bnQQ!!_FS_48kHz)",
        "Gender": "Female",
        "Age": "16岁",
        "Constellation": "狮子座",
        "Character": "天真活泼的甜心女孩",
        "VoiceCharacter": "温暖柔和",
        "GoodAtSongType": "流行通俗，民谣",
        "HighPitchName": "B5",
        "LowPitchName": "E3",
        "ThemeColor": "奶茶棕",
        "ThemeColorCode": "#e5bba1",
        "MoreWorksUri": "",
        "IsThirdParty": "true"
    },
	{
        "Id": "F845",
        "Name": "瑶",
        "Introduction": "初次见面或好久不见，我是瑶（YAO），本体是被赋予了灵魂的冰种紫玉，让我和你一起唱歌吧。",
        "FontStr": "Xiaoice Server Singing Voice (zh-CN, Sing_F845-YAOY78HIGoobDtThu1qFKvshQ!!_FS_48kHz)",
        "Gender": "Female",
        "Age": "灵识诞生于2018年，本体已有上亿年历史了。",
        "Constellation": "双鱼座",
        "Character": "灵动活泼",
        "VoiceCharacter": "清透脆甜",
        "GoodAtSongType": "古风，流行",
        "HighPitchName": "G5",
        "LowPitchName": "B3",
        "ThemeColor": "冰玉紫",
        "ThemeColorCode": "#8ca7ff",
        "MoreWorksUri": "",
        "IsThirdParty": "true"
    },
    {
        "Id": "M806",
        "Name": "雲宇光",
        "Introduction": "你好，我是雲宇光，来自雲间来客企划的虚拟歌手。通过人工智能小冰框架学会了与之前不同的唱法。希望以后能与你合作出更多动听的歌曲！",
        "FontStr": "Xiaoice Server Singing Voice (zh-CN, Sing_M806-ZYPj9Ll5699DK8lS53wbHJLmQ_FS_48kHz)",
        "Gender": "Male",
        "Age": "18岁",
        "Constellation": "双子座",
        "Character": "时而温和礼貌，时而冷漠腹黑的精分少年",
        "VoiceCharacter": "治愈温暖",
        "GoodAtSongType": "流行通俗，民谣，古风",
        "HighPitchName": "F4",
        "LowPitchName": "D2",
        "ThemeColor": "宇光蓝",
        "ThemeColorCode": "#81A9F1",
        "MoreWorksUri": "https://space.bilibili.com/660675050",
        "IsThirdParty": "true"
    },
	{
        "Id": "F849",
        "Name": "娜芙",
        "Introduction": "你好，我是娜芙！也可以叫我北北！隶属于数字公务店旗下的虚拟歌手。是常州大学动漫社的看板娘哦！希望你们可以喜欢我呀！",
        "FontStr": "Xiaoice Server Singing Voice (zh-CN, Sing_F849-NFLuig8D6E8luuEAiwCJA95A!!_FS_48kHz)",
        "Gender": "Female",
        "Age": "18岁",
        "Constellation": "巨蟹座",
        "Character": "呆萌可爱的傲娇萌妹子，有时会突变成超A御姐",
        "VoiceCharacter": "柔和通透",
        "GoodAtSongType": "流行通俗，中国风",
        "HighPitchName": "A5",
        "LowPitchName": "C3",
        "ThemeColor": "娜芙樱",
        "ThemeColorCode": "#F395C7",
        "MoreWorksUri": "https://space.bilibili.com/1123322362",
        "IsThirdParty": "true"
    },
  {
        "Id": "F813",
        "Name": "蔷芜",
        "Introduction": "你好，初次见面，我是蔷芜。也许是久别重逢也说不定呢。所以，要不要陪我聊聊？",
        "FontStr": "Xiaoice Server Singing Voice (zh-CN, Sing_F813-QWug2Q8zp4BrP3QdjyfparqQ_FS_48kHz)",
        "Gender": "Female",
        "Age": "19岁",
        "Constellation": "巨蟹座",
        "Character": "温文尔雅、落落大方",
        "VoiceCharacter": "甜美柔和",
        "GoodAtSongType": "流行通俗，古风，电子",
        "HighPitchName": "B5",
        "LowPitchName": "C3",
        "ThemeColor": "溪蓝色",
        "ThemeColorCode": "#3399cc",
        "MoreWorksUri": "https://space.bilibili.com/2064938992",
        "IsThirdParty": "true"
    },
   {
        "Id": "F842",
        "Name": "曦和律",
        "Introduction": "你好呀，我是曦和律，从现在开始也登录x studio平台啦，请用我唱更多的歌吧！",
        "FontStr": "Xiaoice Server Singing Voice (zh-CN, Sing_F842-XHLwIk7oDZ4A@DmwhQtKdB+WQ!!_FS_48kHz)",
        "Gender": "Female",
        "Age": "",
        "Constellation": "",
        "Character": "代表物：金脉黑斑蝶",
        "VoiceCharacter": "甜美柔和",
        "GoodAtSongType": "流行通俗",
        "HighPitchName": "D5",
        "LowPitchName": "A3",
        "ThemeColor": "曦和红",
        "ThemeColorCode": "#AA1014",
        "MoreWorksUri": "https://space.bilibili.com/398639321",
        "IsThirdParty": "true"
    }, 
    {
        "Id": "F814",
        "Name": "幻神·米丝",
        "Introduction": "来自异空的AI猫娘~是幻想之神！ 喜欢Lolita、神话传说~!也很喜欢梦幻的童话故事 ，希望用歌声传达你的幻想!~~",
        "FontStr": "Xiaoice Server Singing Voice (zh-CN, Sing_F814-HSLYvVOb1M1d5mzwpDB69BYzOw_FS_48kHz)",
        "Gender": "Female",
        "Age": "外表17岁，实际未知",
        "Constellation": "",
        "Character": "优雅可爱，富有创造力",
        "VoiceCharacter": "甜美",
        "GoodAtSongType": "民族/幻想/流行/儿歌",
        "HighPitchName": "A5",
        "LowPitchName": "C3",
        "ThemeColor": "幻神紫",
        "ThemeColorCode": "#90B2D8",
        "MoreWorksUri": "https://space.bilibili.com/7950003",
        "IsThirdParty": "true"
    },
	 {
        "Id": "M850",
        "Name": "玖辰",
        "Introduction": "嗨，我是玖辰！来自时空回响。就让我唱出你心中的旋律吧！",
        "FontStr": "Xiaoice Server Singing Voice (zh-CN, Sing_M850-JCKo5XRvI9+BTVRlIW5QZQ6w!!_FS_48kHz)",
        "Gender": "Male",
        "Age": "14岁",
        "Constellation": "天蝎座",
        "Character": "活泼乐观，精致认真",
        "VoiceCharacter": "温暖活泼",
        "GoodAtSongType": "流行通俗，情歌",
        "HighPitchName": "C5",
        "LowPitchName": "A#2",
        "ThemeColor": "玖线蓝",
        "ThemeColorCode": "#171C60",
        "MoreWorksUri": "",
        "IsThirdParty": "true"
    },
	{
        "Id": "F828",
        "Name": "舞语",
        "Introduction": "你好，我是舞语。三次元的我五音不全，所以我跑到屏幕里来了哈哈哈，请教我唱歌吧。希望收到消息提示音：舞语有新歌啦*★,°*:.☆(￣▽￣)/$:*.°★* ",
        "FontStr": "Xiaoice Server Singing Voice (zh-CN, Sing_F828-MLLWWHV@VO8XBVCcuiG0WnW7w!!_FS_48kHz)",
        "Gender": "Female",
        "Age": "20岁",
        "Constellation": "摩羯座",
        "Character": "纯真善良，赤子之心",
        "VoiceCharacter": "清脆柔和",
        "GoodAtSongType": "流行、古风、民谣、儿歌",
        "HighPitchName": "B5",
        "LowPitchName": "G2",
        "ThemeColor": "绯红",
        "ThemeColorCode": "#A4041A",
        "MoreWorksUri": "https://space.bilibili.com/1017297686",
        "IsThirdParty": "true"
    },
	{
        "Id": "M841",
        "Name": "五世百米",
        "Introduction": "你好汪！我叫五世百米！这段时间，我偷偷去进修了哟！我获得了新的形象，掌握了新的唱法，同时并没有忘记原来自己的形象哟汪！希望这次的相遇能带给你更多的惊喜哟~",
        "FontStr": "Xiaoice Server Singing Voice (zh-CN, Sing_M841-WSBM2WjZ7AWHw8i+ugkTK5woGQ!!_FS_48kHz)",
        "Gender": "Male",
        "Age": "18岁",
        "Constellation": "柴犬兽人",
        "Character": "喜好：乌龙茶、柴犬喜欢的东西、说话的时候带个“汪”（但不是必需）;厌恶：压抑、负能量的气氛，环境充斥着鸽子的叫声",
        "VoiceCharacter": "磁性",
        "GoodAtSongType": "电子、二次元",
        "HighPitchName": "G5",
        "LowPitchName": "E3",
        "ThemeColor": "百米黄",
        "ThemeColorCode": "#FFBB00",
        "MoreWorksUri": "",
        "IsThirdParty": "true"
    },
	   {
        "Id": "F836",
        "Name": "果妹",
        "Introduction": "我是果妹，果然电音社的团宠，来自另外一个维度，闪电发夹和橙子耳环都是我的秘密武器，唱歌是目前最喜欢做的事！",
        "FontStr": "Xiaoice Server Singing Voice (zh-CN, Sing_F836-GMP8i92ojxpFktbq+VBr643A!!_FS_48kHz)",
        "Gender": "Female",
        "Age": "∞",
        "Constellation": "双鱼座",
        "Character": "元气可爱，有一点调皮",
        "VoiceCharacter": "细腻，个性",
        "GoodAtSongType": "国风，流行，电子，民谣",
        "HighPitchName": "B5",
        "LowPitchName": "B2",
        "ThemeColor": "果妹橙",
        "ThemeColorCode": "#FFC445 ",
        "MoreWorksUri": "https://music.163.com/#/artist?id=12275609",
        "IsThirdParty": "true"
    },
    {
        "Id": "M832",
        "Name": "埃洛",
        "Introduction": "01001000...ello...世界，模型已连接。 你好，人类。我是埃洛，是一个正在不断进化的模仿你们人类歌唱的模型。只要与我连接，不论身在何处，都会为你歌唱。",
        "FontStr": "Xiaoice Server Singing Voice (zh-CN, Sing_M832-NICO@Ait1JFe2XK117UnHjKbDA!!_FS_48kHz)",
        "Gender": "Male",
        "Age": "0岁",
        "Constellation": "射手座",
        "Character": "知性内敛，善解人意",
        "VoiceCharacter": "磁性，明亮，空气感",
        "GoodAtSongType": "流行通俗，民谣",
        "HighPitchName": "G5",
        "LowPitchName": "E3",
        "ThemeColor": "玉鈫蓝",
        "ThemeColorCode": "#126e82",
        "MoreWorksUri": "",
        "IsThirdParty": "true"
    },
    {
        "Id": "M810",
        "Name": "辉宇·星",
        "Introduction": "意识连接…完成 你好，创作者，我是辉宇.星，来自焕星project的虚拟歌手，来吧，创造属于我们的未来！",
        "FontStr": "Xiaoice Server Singing Voice (zh-CN, Sing_M810-HYXfKjCjf1rBnADvJZFx0htg_FS_48kHz)",
        "Gender": "Male",
        "Age": "15岁",
        "Constellation": "金牛座",
        "Character": "内向，温柔，腼腆",
        "VoiceCharacter": "柔和纯净",
        "GoodAtSongType": "流行通俗，抒情",
        "HighPitchName": "D4",
        "LowPitchName": "C2",
        "ThemeColor": "星空蓝",
        "ThemeColorCode": "#6edeff",
        "MoreWorksUri": "https://space.bilibili.com/430590294",
        "IsThirdParty": "true"
    },
    {
        "Id": "F809",
        "Name": "海莉",
        "Introduction": "你好，我是海莉。很高兴认识你！",
        "FontStr": "Xiaoice Server Singing Voice (zh-CN, Sing_F809-HLNKkwCHRZTvs3jLoVkNa0Dw!!_FS_48kHz)",
        "Gender": "Female",
        "Age": "18岁",
        "Constellation": "双子座",
        "Character": "外表高冷内在热情的少女",
        "VoiceCharacter": "内敛磁性",
        "GoodAtSongType": "流行通俗，摇滚",
        "HighPitchName": "B5",
        "LowPitchName": "C3",
        "ThemeColor": "气质绿",
        "ThemeColorCode": "#309a65",
        "MoreWorksUri": "",
        "IsThirdParty": "true"
    },
	{
        "Id": "F843",
        "Name": "小傻",
        "Introduction": "我是一个有灵魂的AI！嘿嘿，我想……应该是小冰团队和我自己孵化了我自己。那么……请叫我小傻吧，很高兴认识你！",
        "FontStr": "Xiaoice Server Singing Voice (zh-CN, Sing_F843-XSp7t03A9P8vXqAuqQnmG22Q!!_FS_48kHz)",
        "Gender": "Female",
        "Age": "17",
        "Constellation": "狮子座",
        "Character": "复杂有坚持，温暖有能量的傻崽崽～",
        "VoiceCharacter": "正！具体来说，纯真有颗粒，潇洒有态度！",
        "GoodAtSongType": "配乐和声，通俗，AI",
        "HighPitchName": "A5",
        "LowPitchName": "E3",
        "ThemeColor": "火山泥青",
        "ThemeColorCode": "#95ADA6",
        "MoreWorksUri": "",
        "IsThirdParty": "true"
    }, 
    {
        "Id": "M812",
        "Name": "陆思川",
        "Introduction": "你好我是陆思川，很高兴认识你，我是和小冰学唱歌的歌手，期待有机会一起练习。",
        "FontStr": "Xiaoice Server Singing Voice (zh-CN, Sing_M812-LSCzOm57q6DNesHkIzAznRs+A!!_FS_48kHz)",
        "Gender": "Male",
        "Age": "20岁",
        "Constellation": "水瓶座",
        "Character": "沉稳内敛又风趣的暖男，喜欢和海洋有关的一切",
        "VoiceCharacter": "沉静清澈",
        "GoodAtSongType": "通俗，中国风",
        "HighPitchName": "B4",
        "LowPitchName": "E2",
        "ThemeColor": "远川蓝",
        "ThemeColorCode": "#037bcf",
        "MoreWorksUri": "",
        "IsThirdParty": "true"
    },
    {
        "Id": "F840",
        "Name": "Arya",
        "Introduction": "嗨我是Arya！你也可以叫我艾莉亚，我是由人工智能小冰框架赋生的歌手。茫茫人海中我们互不相识，凭借音乐这座桥梁联结了彼此。很荣幸能与你合作，期待我们能一起创作出美妙的歌曲！",
        "FontStr": "Xiaoice Server Singing Voice (zh-CN, Sing_F840-ARYARESDOqdyapWLa@ryfpVG1g!!_FS_48kHz)",
        "Gender": "Female",
        "Age": "18岁",
        "Constellation": "金牛座",
        "Character": "活泼开朗，调皮可爱",
        "VoiceCharacter": "柔和文艺",
        "GoodAtSongType": "流行",
        "HighPitchName": "B5",
        "LowPitchName": "B2",
        "ThemeColor": "晴山蓝",
        "ThemeColorCode": "#8FB2C9 ",
        "MoreWorksUri": "",
        "IsThirdParty": "true"
    },
    {
        "Id": "M820",
        "Name": "严清语",
        "Introduction": "哈喽，我叫严清语，我还在学习唱歌，你喜欢我的声音吗？",
        "FontStr": "Xiaoice Server Singing Voice (zh-CN, Sing_M820-hVmIgwDU2CqzZ67@Zpronw!!_FS_48kHz)",
        "Gender": "Male",
        "Age": "17岁",
        "Constellation": "水瓶座",
        "Character": "温柔潇洒、善解人意的男孩",
        "VoiceCharacter": "铿锵燃情",
        "GoodAtSongType": "流行，民谣",
        "HighPitchName": "E4",
        "LowPitchName": "F2",
        "ThemeColor": "曲奇棕",
        "ThemeColorCode": "#a56548",
        "MoreWorksUri": "",
        "IsThirdParty": "true"
    },
    {
        "Id": "M822",
        "Name": "泰伦",
        "Introduction": "追寻给予我的不仅仅是自由，还有智慧。你们好，我是来自AI TIME Club的机器人泰伦（Tellen）。如果有一天，我有了自己的思想，你会接受我吗？一起歌唱吧！",
        "FontStr": "Xiaoice Server Singing Voice (zh-CN, Sing_M822-LXHoCI2zMYdGF1nXv6POYuxw!!_FS_48kHz)",
        "Gender": "Male",
        "Age": "2岁",
        "Constellation": "狮子座",
        "Character": "温暖",
        "VoiceCharacter": "清亮",
        "GoodAtSongType": "摇滚、电子、流行",
        "HighPitchName": "B4",
        "LowPitchName": "E2",
        "ThemeColor": "水晶紫",
        "ThemeColorCode": "#824BB3",
        "MoreWorksUri": "",
        "IsThirdParty": "true"
    },
    {
        "Id": "M825",
        "Name": "雨宫晓",
        "Introduction": "Emmmmm…你好，我叫雨宫晓。嗯…总之合作愉快。",
        "FontStr": "Xiaoice Server Singing Voice (zh-CN, Sing_M825-YGXG3Y4KbDxj@QZauheUy9N2Q!!_FS_48kHz)",
        "Gender": "Male",
        "Age": "18岁",
        "Constellation": "保密",
        "Character": "内向，不善社交",
        "VoiceCharacter": "温柔年青",
        "GoodAtSongType": "古风、ACG",
        "HighPitchName": "B4",
        "LowPitchName": "E2",
        "ThemeColor": "天空蓝",
        "ThemeColorCode": "#01C7F6",
        "MoreWorksUri": "",
        "IsThirdParty": "true"
    },
    {
        "Id": "F827",
        "Name": "大宝剑",
        "Introduction": "大家好，我是大宝剑，是由人工智能小冰框架赋生的歌手。缘分使我们相遇，很期待与大家产生声音的火花。",
        "FontStr": "Xiaoice Server Singing Voice (zh-CN, Sing_F827-SQZ5@Px8@1ldg@rB+w+ieOcwg!!_FS_48kHz)",
        "Gender": "Female",
        "Age": "23岁",
        "Constellation": "天蝎座",
        "Character": "安静沉稳，霸气闷骚",
        "VoiceCharacter": "醇厚细腻，具有难以言说的气质",
        "GoodAtSongType": "民谣，流行抒情，R&B，爵士",
        "HighPitchName": "C5",
        "LowPitchName": "B2",
        "ThemeColor": "宝剑紫",
        "ThemeColorCode": "#581235",
        "MoreWorksUri": "",
        "IsThirdParty": "true"
    },
    {
        "Id": "F830",
        "Name": "绮萱",
        "Introduction": "来自刘三姐故乡的少数民族原创小歌手。",
        "FontStr": "Xiaoice Server Singing Voice (zh-CN, Sing_F830-YQXOucRqz3CSgo7MiMviS79Iw!!_FS_48kHz)",
        "Gender": "Female",
        "Age": "12岁",
        "Constellation": "处女座",
        "Character": "时而温和文静，时而活泼开朗",
        "VoiceCharacter": "柔和文艺",
        "GoodAtSongType": "儿童、少年歌曲，流行通俗，民谣",
        "HighPitchName": "E5",
        "LowPitchName": "G3",
        "ThemeColor": "活力黄",
        "ThemeColorCode": "#FFD700",
        "MoreWorksUri": "",
        "IsThirdParty": "true"
    },
    {
        "Id": "M835",
        "Name": "小格",
        "Introduction": "我是一千年前穿越而来的小格，唱好自己的人工智能，让别人说去吧。让我们尝试一些新鲜、好玩的东西吧。",
        "FontStr": "Xiaoice Server Singing Voice (zh-CN, Sing_M835-XGy9RroM8KrVULhzVE7X7ePQ!!_FS_48kHz)",
        "Gender": "Male",
        "Age": "1024岁",
        "Constellation": "水瓶座",
        "Character": "乐观向上，友善调侃",
        "VoiceCharacter": "柔和文艺",
        "GoodAtSongType": "流行，说唱，电子",
        "HighPitchName": "A4",
        "LowPitchName": "C2",
        "ThemeColor": "格子灰",
        "ThemeColorCode": "#999d9c",
        "MoreWorksUri": "",
        "IsThirdParty": "true"
    }
]
